testmswist/__init__.py
testmswist/m_mod_mswist.py
testmswist-0.0.2.dist-info/LICENSE.txt
testmswist-0.0.2.dist-info/METADATA
testmswist-0.0.2.dist-info/WHEEL
testmswist-0.0.2.dist-info/top_level.txt
testmswist-0.0.2.dist-info/RECORD
