Metadata-Version: 2.1
Name: testmswist
Version: 0.0.2
Summary: My test package
Author-email: MA <mail@mail.pl>
License: MIT License
Keywords: testmswist,name,surname,fun function
Classifier: Framework :: IDLE
Classifier: Natural Language :: Polish
Requires-Python: <=3.0
License-File: LICENSE.txt
Requires-Dist: python-version (>='3.0')
Requires-Dist: numpy
